find_sshable/__init__.py
find_sshable/command.py
find_sshable/net.py
find_sshable/sshconf.py
find_sshable/tools.py
find_sshable-0.2.3.dist-info/LICENSE
find_sshable-0.2.3.dist-info/METADATA
find_sshable-0.2.3.dist-info/WHEEL
find_sshable-0.2.3.dist-info/entry_points.txt
find_sshable-0.2.3.dist-info/top_level.txt
find_sshable-0.2.3.dist-info/RECORD
