Metadata-Version: 2.1
Name: find-sshable
Version: 0.2.3
Summary: Tool to find ssh-able devices on your network.
Home-page: https://github.com/riklopfer/find-sshable
Author: Russell Klopfer
Author-email: russell.klopfer@gmail.com
License: GPL 3.0
Platform: UNKNOWN
License-File: LICENSE
Requires-Dist: python3-nmap
Requires-Dist: tqdm-thread ; python_version >= "3.5"
